{
  "session_id": "b7471d41-9ad9-485e-8990-178afdd1483f",
  "resume": {
    "raw_text": "ASHISH GARG\nMadhya Pradesh, India\nashishgargofficial6548@gmail.com | +91 97523 37964 | linkedin.com/in/ashish-garg-2b896432a\nEDUCATION\nB.Tech in Computer Science and Design Expected 2028\nMadhav Institute of Technology and Science, Gwalior CGPA: 8.00/10.0\nEXPERIENCE\nGraphic Designer March 2025 – September 2025\nBlue Planet Info Solutions, Mumbai, Maharashtra\n• Designed 40+ recruitment posters and visual creatives for multiple companies, effectively communicating\njob roles and employer branding across digital platforms\n• Collaboratedwithinternalteamstodeliveron-brandcreativeswithintightdeadlines, supportingmultiple\nconcurrent hiring drives\n• Managed company social media accounts with consistent posting schedule, improving reach and engage-\nment by 25–30% during active recruitment periods\nFreelance Designer June 2022 – Present\nSelf-Employed\n• Delivered 20+ freelance design projects including posters, social media creatives, and branding assets\nwith 100% on-time delivery\n• Collaborated directly with clients to translate ideas into high-quality visual designs, achieving 90%+\nclient satisfaction rate\n• Managedprojectsend-to-endfromconcepttofinaldeliverywhilebalancingmultipleclientssimultaneously\nFundraising Intern May 2021 – June 2021\nMuskurahat Foundation\n• Engaged20+potentialdonorsthroughdirectcommunication,helpingraise2,000forfoundationinitiatives\n• Achieved 100% of assigned fundraising targets within stipulated timeframe\n• Strengthened donor engagement processes, contributing to improved response rates\nPROJECTS\nUniCred – College Engagement Platform April 2025 – June 2025\nunicred.vercel.app\n• Designed user-centered interfaces for 10+ core features including event participation, leaderboards, and\ncertificate uploads\n• Developed 20+ high-fidelity prototype screens, increasing student engagement by 30% during testing\n• Conducted iterative user testing with 15+ students to refine layouts and accessibility\nGreenScore AI – Sustainability Metrics Platform October 2025 – December 2025\ngreenscore-six.vercel.app\n• Crafted engaging dashboards to display tree-count and sustainability metrics for 100+ simulated users\n• Designed interactive visualizations reducing user comprehension time of satellite analysis by 40%\n• Iterated on layouts and visual hierarchy based on feedback from 10+ test users\nSKILLS\nDesign: UI/UX Design, Graphic Design, Figma, Adobe Creative Suite, Prototyping, Visual Design\nDevelopment: Web Development, App Development, HTML/CSS\nOther: Marketing, Social Media Management, Client Communication, Project Management\nPORTFOLIO\nBehance: behance.net/ashishgargofficial | Figma: figma.com/@itsishhh2346",
    "education": [
      {
        "institution": "B.Tech in Computer Science and Design",
        "degree": "B.Tech",
        "field_of_study": null,
        "start_date": "2028",
        "end_date": null,
        "gpa": null,
        "source_text": "B.Tech in Computer Science and Design"
      },
      {
        "institution": "Madhav Institute of Technology and Science",
        "degree": "M.A.",
        "field_of_study": null,
        "start_date": null,
        "end_date": null,
        "gpa": "8.00/10.0",
        "source_text": "Madhav Institute of Technology and Science, Gwalior"
      }
    ],
    "experience": [
      {
        "company": "Graphic Designer",
        "title": "Graphic Designer",
        "start_date": "Present",
        "end_date": null,
        "description": " Designed 40+ recruitment posters and visual creatives for multiple companies, effectively communicating Collaboratedwithinternalteamstodeliveron-brandcreativeswithintightdeadlines, supportingmultiple Managed company social media accounts with consistent posting schedule, improving reach and engage-",
        "responsibilities": [
          "Designed 40+ recruitment posters and visual creatives for multiple companies, effectively communicating",
          "Collaboratedwithinternalteamstodeliveron-brandcreativeswithintightdeadlines, supportingmultiple",
          "Managed company social media accounts with consistent posting schedule, improving reach and engage-"
        ],
        "source_text": "Graphic Designer"
      },
      {
        "company": "Freelance Designer",
        "title": "Freelance Designer",
        "start_date": "2022",
        "end_date": "Present",
        "description": " Delivered 20+ freelance design projects including posters, social media creatives, and branding assets Collaborated directly with clients to translate ideas into high-quality visual designs, achieving 90%+ Managedprojectsend-to-endfromconcepttofinaldeliverywhilebalancingmultipleclientssimultaneously",
        "responsibilities": [
          "Delivered 20+ freelance design projects including posters, social media creatives, and branding assets",
          "Collaborated directly with clients to translate ideas into high-quality visual designs, achieving 90%+",
          "Managedprojectsend-to-endfromconcepttofinaldeliverywhilebalancingmultipleclientssimultaneously"
        ],
        "source_text": "Freelance Designer"
      },
      {
        "company": "Fundraising Intern",
        "title": "Fundraising Intern",
        "start_date": "2021",
        "end_date": "2021",
        "description": " Engaged20+potentialdonorsthroughdirectcommunication,helpingraise2,000forfoundationinitiatives Achieved 100% of assigned fundraising targets within stipulated timeframe Strengthened donor engagement processes, contributing to improved response rates",
        "responsibilities": [
          "Engaged20+potentialdonorsthroughdirectcommunication,helpingraise2,000forfoundationinitiatives",
          "Achieved 100% of assigned fundraising targets within stipulated timeframe",
          "Strengthened donor engagement processes, contributing to improved response rates"
        ],
        "source_text": "Fundraising Intern"
      }
    ],
    "projects": [
      {
        "name": "UniCred – College Engagement Platform",
        "description": "",
        "technologies": [],
        "url": null,
        "source_text": "UniCred – College Engagement Platform"
      },
      {
        "name": "April 2025 – June 2025",
        "description": "",
        "technologies": [],
        "url": null,
        "source_text": "April 2025 – June 2025"
      },
      {
        "name": "unicred.vercel.app",
        "description": " Designed user-centered interfaces for 10+ core features including event participation, leaderboards, and",
        "technologies": [],
        "url": null,
        "source_text": "unicred.vercel.app"
      },
      {
        "name": "certificate uploads",
        "description": " Developed 20+ high-fidelity prototype screens, increasing student engagement by 30% during testing Conducted iterative user testing with 15+ students to refine layouts and accessibility",
        "technologies": [],
        "url": null,
        "source_text": "certificate uploads"
      },
      {
        "name": "GreenScore AI – Sustainability Metrics Platform",
        "description": "",
        "technologies": [],
        "url": null,
        "source_text": "GreenScore AI – Sustainability Metrics Platform"
      },
      {
        "name": "October 2025 – December 2025",
        "description": "",
        "technologies": [],
        "url": null,
        "source_text": "October 2025 – December 2025"
      },
      {
        "name": "greenscore-six.vercel.app",
        "description": " Crafted engaging dashboards to display tree-count and sustainability metrics for 100+ simulated users Designed interactive visualizations reducing user comprehension time of satellite analysis by 40% Iterated on layouts and visual hierarchy based on feedback from 10+ test users",
        "technologies": [],
        "url": null,
        "source_text": "greenscore-six.vercel.app"
      }
    ],
    "certifications": [],
    "skills": [
      {
        "name": "html",
        "canonical_name": "HTML",
        "category": "programming_languages",
        "confidence": "high",
        "source_text": "gn\nDevelopment: Web Development, App Development, HTML/CSS\nOther: Marketing, Social Media Management, Cl",
        "line_number": null
      },
      {
        "name": "css",
        "canonical_name": "CSS",
        "category": "programming_languages",
        "confidence": "high",
        "source_text": "velopment: Web Development, App Development, HTML/CSS\nOther: Marketing, Social Media Management, Client",
        "line_number": null
      },
      {
        "name": "figma",
        "canonical_name": "Figma",
        "category": "tools",
        "confidence": "high",
        "source_text": "Design: UI/UX Design, Graphic Design, Figma, Adobe Creative Suite, Prototyping, Visual Design",
        "line_number": null
      },
      {
        "name": "communication",
        "canonical_name": "Communication",
        "category": "soft_skills",
        "confidence": "high",
        "source_text": "Other: Marketing, Social Media Management, Client Communication, Project Management",
        "line_number": null
      },
      {
        "name": "project management",
        "canonical_name": "Project Management",
        "category": "soft_skills",
        "confidence": "high",
        "source_text": "g, Social Media Management, Client Communication, Project Management",
        "line_number": null
      },
      {
        "name": "web development",
        "canonical_name": "Web Development",
        "category": "other",
        "confidence": "high",
        "source_text": "ve Suite, Prototyping, Visual Design\nDevelopment: Web Development, App Development, HTML/CSS\nOther: Marketing, Soci",
        "line_number": null
      },
      {
        "name": "app development",
        "canonical_name": "Mobile Development",
        "category": "other",
        "confidence": "high",
        "source_text": "ping, Visual Design\nDevelopment: Web Development, App Development, HTML/CSS\nOther: Marketing, Social Media Manageme",
        "line_number": null
      },
      {
        "name": "graphic design",
        "canonical_name": "Graphic Design",
        "category": "tools",
        "confidence": "high",
        "source_text": "Design: UI/UX Design, Graphic Design, Figma, Adobe Creative Suite, Prototyping, Visual",
        "line_number": null
      },
      {
        "name": "ui/ux",
        "canonical_name": "UI/UX Design",
        "category": "tools",
        "confidence": "high",
        "source_text": "Design: UI/UX Design, Graphic Design, Figma, Adobe Creative Sui",
        "line_number": null
      },
      {
        "name": "visual design",
        "canonical_name": "Visual Design",
        "category": "tools",
        "confidence": "high",
        "source_text": "Design, Figma, Adobe Creative Suite, Prototyping, Visual Design\nDevelopment: Web Development, App Development, HT",
        "line_number": null
      },
      {
        "name": "social media",
        "canonical_name": "Social Media",
        "category": "tools",
        "confidence": "high",
        "source_text": "ment, App Development, HTML/CSS\nOther: Marketing, Social Media Management, Client Communication, Project Managem",
        "line_number": null
      },
      {
        "name": ".net",
        "canonical_name": ".NET",
        "category": "frameworks",
        "confidence": "high",
        "source_text": "ion, Project Management\nPORTFOLIO\nBehance: behance.net/ashishgargofficial | Figma: figma.com/@itsishhh23",
        "line_number": null
      }
    ],
    "contact_info": {},
    "parsing_warnings": []
  },
  "job_description": null,
  "evaluation": null,
  "created_at": "2026-02-07T00:02:08.350792",
  "updated_at": "2026-02-07T00:02:08.351843"
}